simod/__init__.py
simod/batching/__init__.py
simod/batching/discovery.py
simod/batching/types.py
simod/branch_rules/__init__.py
simod/branch_rules/discovery.py
simod/branch_rules/types.py
simod/cli.py
simod/cli_formatter.py
simod/control_flow/__init__.py
simod/control_flow/discovery.py
simod/control_flow/lib/bpmn-layout-1.0.6-jar-with-dependencies.jar
simod/control_flow/lib/split-miner-1.7.1-all.jar
simod/control_flow/optimizer.py
simod/control_flow/settings.py
simod/data_attributes/__init__.py
simod/data_attributes/discovery.py
simod/data_attributes/types.py
simod/event_log/__init__.py
simod/event_log/event_log.py
simod/event_log/preprocessor.py
simod/extraneous_delays/__init__.py
simod/extraneous_delays/optimizer.py
simod/extraneous_delays/types.py
simod/extraneous_delays/utilities.py
simod/metrics.py
simod/prioritization/__init__.py
simod/prioritization/discovery.py
simod/prioritization/types.py
simod/resource_model/__init__.py
simod/resource_model/optimizer.py
simod/resource_model/repair.py
simod/resource_model/settings.py
simod/runtime_meter.py
simod/settings/__init__.py
simod/settings/common_settings.py
simod/settings/control_flow_settings.py
simod/settings/extraneous_delays_settings.py
simod/settings/preprocessing_settings.py
simod/settings/resource_model_settings.py
simod/settings/simod_settings.py
simod/simod.py
simod/simulation/__init__.py
simod/simulation/parameters/BPS_model.py
simod/simulation/parameters/__init__.py
simod/simulation/prosimos.py
simod/utilities.py
simod-5.1.6.dist-info/LICENSE
simod-5.1.6.dist-info/METADATA
simod-5.1.6.dist-info/WHEEL
simod-5.1.6.dist-info/entry_points.txt
simod-5.1.6.dist-info/RECORD
