Metadata-Version: 2.3
Name: simod
Version: 5.1.6
Summary: Simod is a Python tool for automated discovery of business process simulation models from event logs.
Author: Ihar Suvorau
Author-email: ihar.suvorau@gmail.com
Requires-Python: >=3.9,<3.12
Classifier: Programming Language :: Python :: 3
Classifier: Programming Language :: Python :: 3.9
Classifier: Programming Language :: Python :: 3.10
Classifier: Programming Language :: Python :: 3.11
Requires-Dist: PyYAML (>=6.0,<7.0)
Requires-Dist: click (>=8.1.3,<9.0.0)
Requires-Dist: extraneous-activity-delays (>=2.1.21,<3.0.0)
Requires-Dist: hyperopt (>=0.2.7,<0.3.0)
Requires-Dist: log-distance-measures (>=2.0.0,<3.0.0)
Requires-Dist: lxml (>=5.3.0,<6.0.0)
Requires-Dist: matplotlib (>=3.6.0,<4.0.0)
Requires-Dist: networkx (>=3.2.1,<4.0.0)
Requires-Dist: numpy (>=1.24.23,<2.0.0)
Requires-Dist: openxes-cli-py (>=0.1.15,<0.2.0)
Requires-Dist: pandas (>=2.1.0,<3.0.0)
Requires-Dist: pendulum (>=3.0.0,<4.0.0)
Requires-Dist: pix-framework (>=0.13.17,<0.14.0)
Requires-Dist: prosimos (>=2.0.6,<3.0.0)
Requires-Dist: pydantic (>=2.3.0,<3.0.0)
Requires-Dist: python-dotenv (>=1.0.0,<2.0.0)
Requires-Dist: python-multipart (>=0.0.12,<0.0.13)
Requires-Dist: pytz (>=2024.2,<2025.0)
Requires-Dist: requests (>=2.28.2,<3.0.0)
Requires-Dist: scipy (>=1.13.0,<2.0.0)
Requires-Dist: statistics (>=1.0.3.5,<2.0.0.0)
Requires-Dist: tqdm (>=4.64.1,<5.0.0)
Requires-Dist: xmltodict (>=0.13.0,<0.14.0)
